setup.py
distributions/Binomialdistribution.py
distributions/Gaussiandistribution.py
distributions/Generaldistribution.py
distributions/__init__.py
gaussian_binomial_package.egg-info/PKG-INFO
gaussian_binomial_package.egg-info/SOURCES.txt
gaussian_binomial_package.egg-info/dependency_links.txt
gaussian_binomial_package.egg-info/not-zip-safe
gaussian_binomial_package.egg-info/top_level.txt