Metadata-Version: 1.0
Name: gaussian-binomial-package
Version: 0.1
Summary: Gaussian distributions, Binomial distributions
Home-page: UNKNOWN
Author: Ssentumbwe Enoch
Author-email: UNKNOWN
License: UNKNOWN
Platform: UNKNOWN
